README.md
setup.py
lowess/__init__.py
lowess/lowess.py
lowess.egg-info/PKG-INFO
lowess.egg-info/SOURCES.txt
lowess.egg-info/dependency_links.txt
lowess.egg-info/not-zip-safe
lowess.egg-info/requires.txt
lowess.egg-info/top_level.txt