Metadata-Version: 2.1
Name: lowess
Version: 1.0.3
Summary: Lowess smoothed as defined for STATA 13.
Home-page: http://github.com/CCGE-Cambridge/lowess
Author: Andrew Lee
License: UNKNOWN
Platform: UNKNOWN
Classifier: Intended Audience :: Science/Research
Classifier: Operating System :: OS Independent
Classifier: Programming Language :: Python :: 3
